agentwrap/__init__.py
agentwrap/agent.py
agentwrap/base_server.py
agentwrap/config.py
agentwrap/events.py
agentwrap/examples.py
agentwrap/prompts.py
agentwrap/agents/__init__.py
agentwrap/agents/codex_agent.py
agentwrap/cli/__init__.py
agentwrap/cli/formatting.py
agentwrap/cli/main.py
agentwrap/server/__init__.py
agentwrap/server/dynamic_mcp_bridge.py
agentwrap/server/dynamic_mcp_server.py
agentwrap/server/types.py
agentwrap/servers/__init__.py
agentwrap/servers/openai_compatible.py
agentwrap-0.1.1.dist-info/METADATA
agentwrap-0.1.1.dist-info/WHEEL
agentwrap-0.1.1.dist-info/entry_points.txt
agentwrap-0.1.1.dist-info/RECORD
