Metadata-Version: 2.4
Name: agentwrap
Version: 0.1.1
Summary: Wrap agents, ship APIs - Turn agent CLIs into libraries and OpenAI-compatible servers
Project-URL: Homepage, https://github.com/dashi0/agentwrap
Project-URL: Repository, https://github.com/dashi0/agentwrap
Project-URL: Issues, https://github.com/dashi0/agentwrap/issues
Author: AgentWrap Contributors
License: MIT
Keywords: agent,ai,api,capsule,codex,mcp,openai,wrapper
Classifier: Development Status :: 3 - Alpha
Classifier: Intended Audience :: Developers
Classifier: License :: OSI Approved :: MIT License
Classifier: Programming Language :: Python :: 3
Classifier: Programming Language :: Python :: 3.8
Classifier: Programming Language :: Python :: 3.9
Classifier: Programming Language :: Python :: 3.10
Classifier: Programming Language :: Python :: 3.11
Classifier: Programming Language :: Python :: 3.12
Classifier: Topic :: Scientific/Engineering :: Artificial Intelligence
Requires-Python: >=3.8
Requires-Dist: click>=8.1.7
Requires-Dist: fastapi>=0.104.0
Requires-Dist: jsonschema>=4.25.1
Requires-Dist: pyyaml>=6.0.1
Requires-Dist: toml>=0.10.2
Requires-Dist: uvicorn>=0.24.0
Provides-Extra: dev
Requires-Dist: httpx>=0.25.0; extra == 'dev'
Requires-Dist: pytest-asyncio>=0.21.0; extra == 'dev'
Requires-Dist: pytest-cov>=4.1.0; extra == 'dev'
Requires-Dist: pytest-mock>=3.12.0; extra == 'dev'
Requires-Dist: pytest>=7.4.0; extra == 'dev'
Requires-Dist: ruff>=0.1.0; extra == 'dev'
